linki/__init__.py
linki/__main__.py
linki/article.py
linki/change.py
linki/config.py
linki/connection.py
linki/contribution.py
linki/draft.py
linki/editor.py
linki/id.py
linki/inbox.py
linki/main.py
linki/outbox.py
linki/py.typed
linki/repository.py
linki/subscription.py
linki/templates/base.html
linki/templates/many.html
linki/templates/one.html
linki/testing/__init__.py
linki/testing/connection/__init__.py
linki/testing/connection/test_connection.py
linki/testing/editor/__init__.py
linki/testing/editor/test_editor.py
linki/testing/editor/test_file_editor.py
linki/testing/main/__init__.py
linki/testing/main/test_complex_cases.py
linki/testing/main/test_successful_output.py
linki/testing/server/__init__.py
linki/testing/server/test_happy_path.py
linki/testing/strategies/__init__.py
linki/testing/strategies/article.py
linki/testing/strategies/draft.py
linki/testing/strategies/type.py
linki/title.py
linki/url.py
linki/user.py
linki/viewer.py
linki-0.0.15.dist-info/LICENSE
linki-0.0.15.dist-info/METADATA
linki-0.0.15.dist-info/WHEEL
linki-0.0.15.dist-info/entry_points.txt
linki-0.0.15.dist-info/RECORD
