Metadata-Version: 2.1
Name: linki
Version: 0.0.15
Summary: Distributed wiki tools
License: GPL-3.0-or-later
Requires-Python: >=3.8,<4.0
Classifier: Development Status :: 4 - Beta
Classifier: License :: OSI Approved :: GNU General Public License v3 (GPLv3)
Classifier: License :: OSI Approved :: GNU General Public License v3 or later (GPLv3+)
Classifier: Operating System :: OS Independent
Classifier: Programming Language :: Python :: 3
Classifier: Programming Language :: Python :: 3.8
Classifier: Programming Language :: Python :: 3.9
Classifier: Programming Language :: Python :: 3.10
Classifier: Programming Language :: Python :: 3.11
Requires-Dist: bottle (>=0.12.25,<0.13.0)
Requires-Dist: msgspec (>=0.16.0,<0.17.0)
Requires-Dist: pypandoc (>=1.11,<2.0)
Requires-Dist: requests (>=2.31.0,<3.0.0)
Requires-Dist: typer (>=0.9.0,<0.10.0)
Requires-Dist: typing-extensions (>=4.7.0,<5.0.0)
Requires-Dist: werkzeug (>=2.3.6,<3.0.0)
